common/__init__.py
common/dtos.py
common/oauth2_storage.py
common/oauth_user_auth_tokens_service.py
essentials_kit_management/__init__.py
essentials_kit_management/admin.py
essentials_kit_management/app.py
essentials_kit_management/adapters/__init__.py
essentials_kit_management/adapters/service_adapter.py
essentials_kit_management/api_specs/__init__.py
essentials_kit_management/conf/__init__.py
essentials_kit_management/conf/settings.py
essentials_kit_management/constants/__init__.py
essentials_kit_management/constants/config.py
essentials_kit_management/constants/constants.py
essentials_kit_management/constants/enums.py
essentials_kit_management/constants/exception_messages.py
essentials_kit_management/dtos/__init__.py
essentials_kit_management/dtos/dtos.py
essentials_kit_management/entities/__init__.py
essentials_kit_management/exceptions/__init__.py
essentials_kit_management/exceptions/exceptions.py
essentials_kit_management/interactors/__init__.py
essentials_kit_management/interactors/dtos.py
essentials_kit_management/interactors/get_form_interactor.py
essentials_kit_management/interactors/get_forms_interactor.py
essentials_kit_management/interactors/get_order_details_of_form_interactor.py
essentials_kit_management/interactors/get_pay_through_details_interactor.py
essentials_kit_management/interactors/get_transactions_details_interactor.py
essentials_kit_management/interactors/get_wallet_balance_interactor.py
essentials_kit_management/interactors/get_wallet_balance_with_transactions_interactor.py
essentials_kit_management/interactors/get_wallet_transactions_details_interactor.py
essentials_kit_management/interactors/login_interactor.py
essentials_kit_management/interactors/logout_interactor.py
essentials_kit_management/interactors/post_form_interactor.py
essentials_kit_management/interactors/post_verification_details_interactor.py
essentials_kit_management/interactors/presenters/__init__.py
essentials_kit_management/interactors/presenters/presenter_interface.py
project_raj-0.0.1.dist-info/METADATA
project_raj-0.0.1.dist-info/WHEEL
project_raj-0.0.1.dist-info/top_level.txt
project_raj-0.0.1.dist-info/RECORD
