Metadata-Version: 2.1
Name: project-raj
Version: 0.0.1
Summary: UNKNOWN
Home-page: UNKNOWN
Author: Rajesh Kumar
Author-email: rajesh.ganjikunta@ibhubs.co.in
License: MIT
Platform: UNKNOWN
Classifier: Programming Language :: Python :: 3
Classifier: License :: OSI Approved :: MIT License
Classifier: Operating System :: OS Independent
